<document xml:lang="fit" id="no_id"><header><title>Nuorisotalot ja kohtauspaikat lapsile ja nuorile - Umeå kommun</title><genre code="admin"/><author><unknown/></author><wordcount>139</wordcount><conversion_status type="standard"/><availability><license type="standard"/></availability><multilingual/><origFileName>https://www.umea.se/kommunochpolitik/languages/meankieli/lapsetjakoulutus/nuorisotalotjakohtauspaikatlapsilejanuorile.4.640818217563dc9fe53140.html</origFileName><metadata><uncomplete/></metadata><version>XSLtemplate $Revision: 187360 $; file-specific xsl  Revision; common.xsl  $Revision$; </version></header><body><p xml:lang="swe">Denna sida använder cookies. För mer information kan du</p>
<p xml:lang="swe">läsa om kakor här.</p>
<p xml:lang="koi"></p>
<p xml:lang="swe">Sök på webbplatsen</p>
<p xml:lang="koi"></p>
<p xml:lang="pol">Meny</p>
<p type="title" xml:lang="fkv">Nuorisotalot ja kohtauspaikat lapsile ja nuorile</p>
<p type="title" xml:lang="swe">Nuorisotalot ja kohtauspaikat lapsile ja nuorile (Fritidsgårdar och mötesplatser för barn och unga)</p>
<p xml:lang="fin">Uumajan kunta on töissä nuorten vapa-aijan kans monela tavala. Met luoma kohtauspaikkoja 13–25 vuotisten lapsile ja nuorile. Nuorisotalot suuntautuvat nuorhiin jokka on 13–17 vuen välissä ja meän nuorten talo on Hamnmagasinet kaupunkin kesustassa ja Ersbodassa meilä on toiminta nuorile jokka on 15–25 vuen välissä. Uumajan kunta tarjoaa kans sattunhaisia kohtauspaikkoja, esimerkiks kesätoimintaa Nydalassa.</p>
<p xml:lang="fin">Met tuema kans nuoria järjestäjiä, tarjoama lupatoimintaa ja aktiviteettiä nuorile joila on liikuntarajoitheita. Kaikki toiminta on huumetonta.</p>
<p xml:lang="nno">Nuorisotaloista sivula www.umea.se/ung Om fritidsgårdar på www.umea.se/ung</p>
<p type="title" xml:lang="swe">Liikuntarajotheile (För funktionshindrade)</p>
<p xml:lang="fkv">Kohtauspaikkoja ja vapa-aijan toimintoja sulle jolla on toiminanrajotheisuus</p>
<p xml:lang="swe">Mötesplatser och fritidsaktiviteter för dig som har en funktionsnedsättning</p>
<p xml:lang="spa"><em type="bold"></em>Sidan publicerades </p>
<p xml:lang="nno"><em type="italic"></em>Facebook  </p>
<p xml:lang="nno"><em type="italic"></em>Twitter  </p>
<p xml:lang="vep"><em type="italic"></em>LinkedIn  </p>
<p xml:lang="isl"><em type="italic"></em>Mail  </p>
</body></document>
