<document xml:lang="fit" id="no_id"><header><title/><genre code="admin"/><author><unknown/></author><wordcount>177</wordcount><conversion_status type="standard"/><availability><license type="standard"/></availability><multilingual/><origFileName>https://www.kalix.se/kommun/nationella-minoriteter/meankieli/Yhteyshenkilot---Kontaktpersoner/</origFileName><metadata><uncomplete/></metadata><version>XSLtemplate $Revision$; file-specific xsl  Revision; common.xsl  $Revision$; </version></header>
<body>
<p xml:lang="deu">Yhteyshenkilöt - Kontaktpersoner</p>
<p xml:lang="eng">Skip to content</p>
<list><p type="listitem" xml:lang="tur"></p>
<p type="listitem" xml:lang="tur"></p>
<p type="listitem" xml:lang="tur"></p>
<p type="listitem" xml:lang="tur"></p>
<p type="listitem" xml:lang="tur"></p>
</list><p type="title" xml:lang="olo">Kalix Kommun</p>
<p xml:lang="tur"></p>
<p xml:lang="tur"></p>
<p xml:lang="tur"></p>
<p xml:lang="tur"></p>
<p xml:lang="nno">Meny  Stäng</p>
<p xml:lang="isl">Sök</p>
<p xml:lang="isl">Sök</p>
<p type="title" xml:lang="deu">Yhteyshenkilöt - Kontaktpersoner</p>
<p xml:lang="fkv">Sie voit soittaa eli kirjottaa meile ko sie tarttet apua ja halvat puhua meänkieltä tai suomea. Pääset alkhuun ja met ohjaama sinun asian etheenpäin jos se ei kuulu meile. Jos tarttet niin met voima kans sopia henkilökohtasen möötin.</p>
<p xml:lang="est"><em type="italic">Maria Vanhapiha Bergström, Koordinaattori </em></p>
<p xml:lang="vep"><em type="italic">070-287 46 94 maria.vanhapihabergstrom@kalix.se </em></p>
<p type="title" xml:lang="olo">Esikoulu</p>
<p xml:lang="fin"><em type="italic">Riitta Väyrynen </em>Lyrans förskola, Solen 0923-653 79 riitta.vayrynen@edu.kalix.se </p>
<p xml:lang="fin"><em type="italic">Sari Leskinen </em>Djuptjärns förskola, Åkerbäret 0923-653 58 Sari.Leskinen@edu.kalix.se </p>
<p xml:lang="fin"><em type="italic">Tanja Stenberg </em>Nystads förskola, Lärkan 0923-653 91 Tanja.Stenberg@kalix.se <em type="italic"></em></p>
<p type="title" xml:lang="fkv">Sulle, joka halvat puhua meänkieltä taikka suomea sosiaalitoimen työntekijän kans</p>
<p xml:lang="fin"><em type="italic">Kristina Henriksson </em>Yksikköpäälikkö, Rosengården 0923-654 74 tai 076-104 88 09 kristina.henriksson@kalix.se </p>
<p xml:lang="fin"><em type="italic">Maria Eliasson </em>Yksikköpäälikkö, Näsbygården 0923-654 77 tai 076-104 88 16 maria.eliasson@kalix.se </p>
<p xml:lang="fin"><em type="italic">Anna Rutberg </em>Yksikköpäälikkö, Kristallgården 0923-656 36 tai 076-104 88 06 </p>
<p xml:lang="fin">anna.rutberg@kalix.se</p>
<p xml:lang="fin"><em type="italic">Tiina Patokoski </em>Yksikköpäälikkö, saihraanhoitajat 0923-656 68 tai 076-145 37 09 tiina.patokoski@kalix.se </p>
<p xml:lang="fin"><em type="italic">Karin Tiensuu Nordqvist </em>Terhveyenhoitaja 0923-650 00 (kunnan väkseli) tai 072-586 50 18 karin.tiensuu-nordqvist@kalix.se </p>
<p xml:lang="fin"><em type="italic">Maria Pohjanen </em>Sosiaalityöntekijä 0923-650 00 (kunnan väkseli) maria.pohjanen@kalix.se </p>
<p xml:lang="fin"><em type="italic">Mikaela Waara </em>Apukäsittelijä 0923-650 00 (kunnan väkseli) ti 076-104 88 09 mikaela.waara@kalix.se </p>
<p xml:lang="swe">Senast uppdaterad:</p>
<p xml:lang="vep">2022-10-13 14:47</p>
</body></document>
